k3d/__init__.py
k3d/_protocol.py
k3d/_version.py
k3d/headless.py
k3d/helpers.py
k3d/k3d_extension.json
k3d/platonic.py
k3d/pytest.ini
k3d/transfer_function_editor.py
k3d/transform.py
k3d/colormaps/__init__.py
k3d/colormaps/basic_color_maps.py
k3d/colormaps/generate_matplotlib_color_maps.py
k3d/colormaps/generate_paraview_color_maps.py
k3d/colormaps/matplotlib_color_maps.py
k3d/colormaps/paraview_color_maps.py
k3d/factory/__init__.py
k3d/factory/common.py
k3d/factory/geometry.py
k3d/factory/plot.py
k3d/factory/points.py
k3d/factory/text.py
k3d/factory/texture.py
k3d/factory/vectors.py
k3d/factory/volumetric.py
k3d/factory/vtk.py
k3d/labextension/package.json
k3d/labextension/static/00b26ac825e2095056396e0553b8ac26d3f8ad158c3826e28b4c45b385c4714a.woff2
k3d/labextension/static/07d8e303ce4fc12b4bb54f1004170dd190a1f3db45d400fe68060df3e0897268.ttf
k3d/labextension/static/08ce98e51b04d58945a301e639e02b6998af29fdfd61a7b8afdd07bbfc479d4a.ttf
k3d/labextension/static/0cdd387c9590a1a9f9794560022dbb59654a7d86f187aa0c81495ad42d3a7308.woff2
k3d/labextension/static/0d85ae7cc30f23790a7f1a58c4a112fdca8aae769b6ba11429af1d98b1b6cb3a.ttf
k3d/labextension/static/0f60d1b897938ec918c8ce073092411baf9438f6739465693ff18b0f9d20b021.woff2
k3d/labextension/static/11e4dc8a6471ff6d6ee561d53d10fde8f7489e798257ff449c5d37c197435605.woff
k3d/labextension/static/138ac28d1663b3037e9c5f52371fa5c63d8324f4a38d22cd573e6ea3a3fd0cf8.ttf
k3d/labextension/static/1c67f068fea8bb09bf099c088b1cf64bd27516a6e07f4684344873564bb66a67.ttf
k3d/labextension/static/1e6f9579e90e2cac37f8f60a597c436e075c114385652b7cbeb0dec0421291b3.ttf
k3d/labextension/static/1ece03f79f95277d57dc7f6b435a74e1379b0d46104a8530286b60ff49369ea0.ttf
k3d/labextension/static/252.85442452fe52e40383dc.js
k3d/labextension/static/252.85442452fe52e40383dc.js.LICENSE.txt
k3d/labextension/static/260.a3dc1e563674d42b3e15.js
k3d/labextension/static/260.a3dc1e563674d42b3e15.js.LICENSE.txt
k3d-2.17.0.dist-info/METADATA
k3d-2.17.0.dist-info/WHEEL
k3d-2.17.0.dist-info/licenses/LICENSE.txt
k3d-2.17.0.dist-info/RECORD
