Metadata-Version: 2.4
Name: k3d
Version: 2.17.0
Dynamic: Author
Dynamic: Author-email
Dynamic: Summary
Dynamic: Project-URL
License: The MIT License
License-File: LICENSE.txt
Keywords: Jupyter,JupyterLab,JupyterLab3
Classifier: Framework :: Jupyter
Classifier: License :: OSI Approved :: MIT License
Classifier: Programming Language :: Python
Classifier: Programming Language :: Python :: 3
Classifier: Programming Language :: Python :: 3.7
Classifier: Programming Language :: Python :: 3.8
Classifier: Programming Language :: Python :: 3.9
Classifier: Programming Language :: Python :: 3.10
Requires-Python: >=3.7
Requires-Dist: deepcomparer
Requires-Dist: ipywidgets<9.0.0,>=7.0.0
Requires-Dist: msgpack
Requires-Dist: numpy
Requires-Dist: traitlets
Requires-Dist: traittypes
Provides-Extra: dev
Requires-Dist: build; extra == 'dev'
Requires-Dist: flask; extra == 'dev'
Requires-Dist: jupyterlab; extra == 'dev'
Requires-Dist: notebook; extra == 'dev'
Requires-Dist: pixelmatch; extra == 'dev'
Requires-Dist: pytest; extra == 'dev'
Requires-Dist: pytest-cov; extra == 'dev'
Requires-Dist: pytest-notebook; extra == 'dev'
Requires-Dist: selenium; extra == 'dev'
Requires-Dist: webdriver-manager; extra == 'dev'
Provides-Extra: examples
Requires-Dist: flask; extra == 'examples'
Requires-Dist: matplotlib; extra == 'examples'
Requires-Dist: mdutils; extra == 'examples'
Requires-Dist: nibabel; extra == 'examples'
Requires-Dist: numba; extra == 'examples'
Requires-Dist: opencv-python; extra == 'examples'
Requires-Dist: pyunpack; extra == 'examples'
Requires-Dist: scikit-image; extra == 'examples'
Requires-Dist: scikit-learn; extra == 'examples'
Requires-Dist: scipy; extra == 'examples'
Requires-Dist: tqdm; extra == 'examples'
Requires-Dist: vtk; extra == 'examples'
